flask_orjson/__init__.py
flask_orjson/provider.py
flask_orjson/py.typed
flask_orjson-2.0.0.dist-info/LICENSE.txt
flask_orjson-2.0.0.dist-info/WHEEL
flask_orjson-2.0.0.dist-info/METADATA
flask_orjson-2.0.0.dist-info/RECORD
